{"playerStatSummaries": [{"wins": 8, "aggregatedStats": {"totalChampionKills": 63, "totalTurretsKilled": 7, "totalMinionKills": 1415, "totalNeutralMinionsKilled": 168, "totalAssists": 70}, "modifyDate": 1453522203000, "playerStatSummaryType": "CAP5x5"}, {"wins": 57, "aggregatedStats": {"totalTurretsKilled": 66, "averageNodeNeutralize": 5, "maxTeamObjective": 1, "totalAssists": 534, "maxNodeNeutralize": 5, "averageChampionsKilled": 6, "averageNodeNeutralizeAssist": 0, "averageTeamObjective": 1, "averageAssists": 6, "maxChampionsKilled": 6, "totalNodeCapture": 4, "maxNodeNeutralizeAssist": 0, "totalNeutralMinionsKilled": 118, "averageTotalPlayerScore": 803, "maxTotalPlayerScore": 803, "maxNodeCaptureAssist": 2, "totalChampionKills": 431, "averageNodeCaptureAssist": 2, "maxObjectivePlayerScore": 532, "totalNodeNeutralize": 5, "totalMinionKills": 4198, "averageObjectivePlayerScore": 532, "maxNodeCapture": 4, "maxCombatPlayerScore": 271, "averageNodeCapture": 4, "maxAssists": 6, "averageCombatPlayerScore": 271, "averageNumDeaths": 4}, "modifyDate": 1453522203000, "playerStatSummaryType": "CoopVsAI"}, {"wins": 0, "aggregatedStats": {}, "modifyDate": 1453522203000, "playerStatSummaryType": "OdinUnranked"}, {"wins": 0, "aggregatedStats": {}, "losses": 0, "modifyDate": 1359945580000, "playerStatSummaryType": "RankedTeam3x3"}, {"wins": 0, "aggregatedStats": {}, "losses": 0, "modifyDate": 1360089756000, "playerStatSummaryType": "RankedTeam5x5"}, {"wins": 17, "aggregatedStats": {"totalChampionKills": 382, "totalTurretsKilled": 13, "totalAssists": 641}, "modifyDate": 1457030353000, "playerStatSummaryType": "AramUnranked5x5"}, {"wins": 5, "aggregatedStats": {"totalChampionKills": 32, "totalTurretsKilled": 7, "totalMinionKills": 475, "totalNeutralMinionsKilled": 154, "totalAssists": 34}, "modifyDate": 1460347251000, "playerStatSummaryType": "Unranked3x3"}, {"wins": 1357, "aggregatedStats": {"totalChampionKills": 19956, "totalTurretsKilled": 2485, "totalMinionKills": 313267, "totalNeutralMinionsKilled": 46924, "totalAssists": 23383}, "modifyDate": 1461422948000, "playerStatSummaryType": "Unranked"}, {"wins": 0, "aggregatedStats": {"totalChampionKills": 8, "totalTurretsKilled": 0, "totalMinionKills": 71, "totalNeutralMinionsKilled": 0, "totalAssists": 6}, "modifyDate": 1461457035000, "playerStatSummaryType": "URF"}, {"wins": 196, "aggregatedStats": {"totalChampionKills": 2581, "totalTurretsKilled": 420, "totalMinionKills": 37653, "totalNeutralMinionsKilled": 17937, "totalAssists": 3124}, "losses": 165, "modifyDate": 1461545653000, "playerStatSummaryType": "RankedSolo5x5"}], "summonerId": 46022}