{"playerStatSummaries": [{"wins": 21, "aggregatedStats": {"totalChampionKills": 298, "totalTurretsKilled": 43, "totalMinionKills": 5251, "totalNeutralMinionsKilled": 1020, "totalAssists": 305}, "modifyDate": 1453297894000, "playerStatSummaryType": "CAP5x5"}, {"wins": 142, "aggregatedStats": {"totalTurretsKilled": 235, "averageNodeNeutralize": 3, "maxTeamObjective": 1, "totalAssists": 1539, "maxNodeNeutralize": 3, "averageChampionsKilled": 5, "averageNodeNeutralizeAssist": 1, "averageTeamObjective": 1, "averageAssists": 7, "maxChampionsKilled": 8, "totalNodeCapture": 20, "maxNodeNeutralizeAssist": 1, "totalNeutralMinionsKilled": 1489, "averageTotalPlayerScore": 895, "maxTotalPlayerScore": 1039, "maxNodeCaptureAssist": 0, "totalChampionKills": 946, "averageNodeCaptureAssist": 0, "maxObjectivePlayerScore": 722, "totalNodeNeutralize": 9, "totalMinionKills": 8652, "averageObjectivePlayerScore": 654, "maxNodeCapture": 8, "maxCombatPlayerScore": 317, "averageNodeCapture": 7, "maxAssists": 11, "averageCombatPlayerScore": 241, "averageNumDeaths": 4}, "modifyDate": 1453297894000, "playerStatSummaryType": "CoopVsAI"}, {"wins": 86, "aggregatedStats": {"totalChampionKills": 681, "totalTurretsKilled": 111, "totalMinionKills": 6143, "totalNeutralMinionsKilled": 673, "totalAssists": 599}, "modifyDate": 1453297894000, "playerStatSummaryType": "CoopVsAI3x3"}, {"wins": 2, "aggregatedStats": {"averageAssists": 7, "averageNodeNeutralize": 5, "averageChampionsKilled": 9, "totalAssists": 28, "maxNodeNeutralize": 10, "maxTeamObjective": 2, "averageNodeNeutralizeAssist": 1, "averageTeamObjective": 2, "maxNodeCapture": 9, "maxChampionsKilled": 18, "totalNodeCapture": 22, "maxNodeNeutralizeAssist": 2, "averageTotalPlayerScore": 1142, "maxTotalPlayerScore": 1944, "maxNodeCaptureAssist": 3, "totalChampionKills": 37, "averageNodeCaptureAssist": 2, "totalNodeNeutralize": 20, "maxObjectivePlayerScore": 1159, "averageObjectivePlayerScore": 688, "maxCombatPlayerScore": 785, "averageNodeCapture": 6, "maxAssists": 10, "averageCombatPlayerScore": 453, "averageNumDeaths": 9}, "modifyDate": 1453297894000, "playerStatSummaryType": "OdinUnranked"}, {"wins": 0, "aggregatedStats": {}, "losses": 0, "modifyDate": 1445305323000, "playerStatSummaryType": "RankedTeam3x3"}, {"wins": 0, "aggregatedStats": {}, "losses": 0, "modifyDate": 1366000707000, "playerStatSummaryType": "RankedTeam5x5"}, {"wins": 46, "aggregatedStats": {"totalChampionKills": 776, "totalTurretsKilled": 31, "totalAssists": 1698}, "modifyDate": 1456539107000, "playerStatSummaryType": "AramUnranked5x5"}, {"wins": 8, "aggregatedStats": {"totalChampionKills": 87, "totalTurretsKilled": 21, "totalMinionKills": 1161, "totalNeutralMinionsKilled": 407, "totalAssists": 107}, "losses": 4, "modifyDate": 1459895830000, "playerStatSummaryType": "RankedSolo5x5"}, {"wins": 2041, "aggregatedStats": {"totalChampionKills": 28591, "totalTurretsKilled": 4099, "totalMinionKills": 468785, "totalNeutralMinionsKilled": 97780, "totalAssists": 35141}, "modifyDate": 1461556670000, "playerStatSummaryType": "Unranked"}, {"wins": 44, "aggregatedStats": {"totalChampionKills": 487, "totalTurretsKilled": 57, "totalMinionKills": 6725, "totalNeutralMinionsKilled": 825, "totalAssists": 587}, "modifyDate": 1461556670000, "playerStatSummaryType": "Unranked3x3"}, {"wins": 0, "aggregatedStats": {"totalChampionKills": 2, "totalTurretsKilled": 0, "totalMinionKills": 35, "totalNeutralMinionsKilled": 0, "totalAssists": 4}, "modifyDate": 1461557886000, "playerStatSummaryType": "URF"}], "summonerId": 62045}