{"playerStatSummaries": [{"wins": 6, "aggregatedStats": {"totalChampionKills": 84, "totalTurretsKilled": 5, "totalMinionKills": 1049, "totalNeutralMinionsKilled": 264, "totalAssists": 89}, "modifyDate": 1453571119000, "playerStatSummaryType": "CAP5x5"}, {"wins": 1, "aggregatedStats": {"totalChampionKills": 20, "totalTurretsKilled": 3, "totalMinionKills": 152, "totalNeutralMinionsKilled": 6, "totalAssists": 6}, "modifyDate": 1453571119000, "playerStatSummaryType": "CoopVsAI"}, {"wins": 3, "aggregatedStats": {"totalChampionKills": 4, "totalTurretsKilled": 1, "totalMinionKills": 117, "totalNeutralMinionsKilled": 5, "totalAssists": 18}, "modifyDate": 1453571119000, "playerStatSummaryType": "CoopVsAI3x3"}, {"wins": 0, "aggregatedStats": {}, "modifyDate": 1453571119000, "playerStatSummaryType": "OdinUnranked"}, {"wins": 0, "aggregatedStats": {}, "losses": 0, "modifyDate": 1396078218000, "playerStatSummaryType": "RankedTeam5x5"}, {"wins": 10, "aggregatedStats": {"totalChampionKills": 176, "totalTurretsKilled": 9, "totalAssists": 322}, "modifyDate": 1457147864000, "playerStatSummaryType": "AramUnranked5x5"}, {"wins": 8, "aggregatedStats": {"totalChampionKills": 83, "totalTurretsKilled": 12, "totalMinionKills": 2243, "totalNeutralMinionsKilled": 61, "totalAssists": 140}, "losses": 7, "modifyDate": 1460255308000, "playerStatSummaryType": "RankedSolo5x5"}, {"wins": 1006, "aggregatedStats": {"totalChampionKills": 14093, "totalTurretsKilled": 1626, "totalMinionKills": 208911, "totalNeutralMinionsKilled": 24097, "totalAssists": 17341}, "modifyDate": 1461385236000, "playerStatSummaryType": "Unranked"}, {"wins": 111, "aggregatedStats": {"totalChampionKills": 1187, "totalTurretsKilled": 144, "totalMinionKills": 16034, "totalNeutralMinionsKilled": 1026, "totalAssists": 1588}, "modifyDate": 1461385236000, "playerStatSummaryType": "Unranked3x3"}, {"wins": 3, "aggregatedStats": {"totalChampionKills": 45, "totalTurretsKilled": 2, "totalMinionKills": 461, "totalNeutralMinionsKilled": 19, "totalAssists": 54}, "modifyDate": 1461525815000, "playerStatSummaryType": "URF"}], "summonerId": 78135}