{"playerStatSummaries": [{"wins": 21, "aggregatedStats": {"totalChampionKills": 437, "totalTurretsKilled": 8, "totalAssists": 855}, "modifyDate": 1453280902000, "playerStatSummaryType": "AramUnranked5x5"}, {"wins": 0, "aggregatedStats": {"totalChampionKills": 14, "totalTurretsKilled": 2, "totalMinionKills": 351, "totalNeutralMinionsKilled": 9, "totalAssists": 19}, "modifyDate": 1453280902000, "playerStatSummaryType": "CAP5x5"}, {"wins": 8, "aggregatedStats": {"totalChampionKills": 50, "totalTurretsKilled": 10, "totalMinionKills": 818, "totalNeutralMinionsKilled": 46, "totalAssists": 66}, "modifyDate": 1453280902000, "playerStatSummaryType": "CoopVsAI"}, {"wins": 0, "aggregatedStats": {"averageAssists": 3, "averageNodeNeutralize": 1, "averageChampionsKilled": 5, "totalAssists": 3, "maxNodeNeutralize": 1, "maxTeamObjective": 0, "averageNodeNeutralizeAssist": 1, "averageTeamObjective": 0, "maxNodeCapture": 3, "maxChampionsKilled": 5, "totalNodeCapture": 3, "maxNodeNeutralizeAssist": 1, "averageTotalPlayerScore": 479, "maxTotalPlayerScore": 479, "maxNodeCaptureAssist": 1, "totalChampionKills": 5, "averageNodeCaptureAssist": 1, "totalNodeNeutralize": 1, "maxObjectivePlayerScore": 282, "averageObjectivePlayerScore": 282, "maxCombatPlayerScore": 197, "averageNodeCapture": 3, "maxAssists": 3, "averageCombatPlayerScore": 197, "averageNumDeaths": 7}, "modifyDate": 1453280902000, "playerStatSummaryType": "OdinUnranked"}, {"wins": 25, "aggregatedStats": {"totalChampionKills": 337, "totalTurretsKilled": 49, "totalMinionKills": 9299, "totalNeutralMinionsKilled": 555, "totalAssists": 386}, "losses": 32, "modifyDate": 1461261811000, "playerStatSummaryType": "RankedSolo5x5"}, {"wins": 0, "aggregatedStats": {}, "losses": 0, "modifyDate": 1406952234000, "playerStatSummaryType": "RankedTeam5x5"}, {"wins": 690, "aggregatedStats": {"totalChampionKills": 8716, "totalTurretsKilled": 984, "totalMinionKills": 140387, "totalNeutralMinionsKilled": 14449, "totalAssists": 11701}, "modifyDate": 1461258504000, "playerStatSummaryType": "Unranked"}, {"wins": 1, "aggregatedStats": {"totalChampionKills": 9, "totalTurretsKilled": 0, "totalMinionKills": 85, "totalNeutralMinionsKilled": 5, "totalAssists": 19}, "modifyDate": 1460166355000, "playerStatSummaryType": "Unranked3x3"}, {"wins": 0, "aggregatedStats": {"totalChampionKills": 2, "totalTurretsKilled": 0, "totalMinionKills": 41, "totalNeutralMinionsKilled": 0, "totalAssists": 5}, "modifyDate": 1461460845000, "playerStatSummaryType": "URF"}], "summonerId": 41150}