{"playerStatSummaries": [{"wins": 25, "aggregatedStats": {"totalChampionKills": 511, "totalTurretsKilled": 21, "totalAssists": 1068}, "modifyDate": 1453340769000, "playerStatSummaryType": "AramUnranked5x5"}, {"wins": 1, "aggregatedStats": {"totalChampionKills": 54, "totalTurretsKilled": 5, "totalMinionKills": 757, "totalNeutralMinionsKilled": 74, "totalAssists": 58}, "modifyDate": 1453340769000, "playerStatSummaryType": "CAP5x5"}, {"wins": 45, "aggregatedStats": {"totalTurretsKilled": 34, "averageNodeNeutralize": 3, "maxTeamObjective": 2, "totalAssists": 332, "maxNodeNeutralize": 8, "averageChampionsKilled": 6, "averageNodeNeutralizeAssist": 2, "averageTeamObjective": 1, "averageAssists": 6, "maxChampionsKilled": 14, "totalNodeCapture": 82, "maxNodeNeutralizeAssist": 7, "totalNeutralMinionsKilled": 135, "averageTotalPlayerScore": 771, "maxTotalPlayerScore": 1677, "maxNodeCaptureAssist": 8, "totalChampionKills": 328, "averageNodeCaptureAssist": 2, "maxObjectivePlayerScore": 1298, "totalNodeNeutralize": 61, "totalMinionKills": 1424, "averageObjectivePlayerScore": 497, "maxNodeCapture": 9, "maxCombatPlayerScore": 611, "averageNodeCapture": 4, "maxAssists": 15, "averageCombatPlayerScore": 273, "averageNumDeaths": 4}, "modifyDate": 1453340769000, "playerStatSummaryType": "CoopVsAI"}, {"wins": 0, "aggregatedStats": {"totalChampionKills": 1, "totalTurretsKilled": 0, "totalMinionKills": 25, "totalNeutralMinionsKilled": 7, "totalAssists": 4}, "modifyDate": 1453340769000, "playerStatSummaryType": "CoopVsAI3x3"}, {"wins": 3, "aggregatedStats": {"averageAssists": 6, "averageNodeNeutralize": 2, "averageChampionsKilled": 4, "totalAssists": 59, "maxNodeNeutralize": 3, "maxTeamObjective": 2, "averageNodeNeutralizeAssist": 2, "averageTeamObjective": 1, "maxNodeCapture": 4, "maxChampionsKilled": 9, "totalNodeCapture": 16, "maxNodeNeutralizeAssist": 3, "averageTotalPlayerScore": 513, "maxTotalPlayerScore": 894, "maxNodeCaptureAssist": 2, "totalChampionKills": 39, "averageNodeCaptureAssist": 2, "totalNodeNeutralize": 10, "maxObjectivePlayerScore": 693, "averageObjectivePlayerScore": 342, "maxCombatPlayerScore": 379, "averageNodeCapture": 2, "maxAssists": 16, "averageCombatPlayerScore": 169, "averageNumDeaths": 6}, "modifyDate": 1453340769000, "playerStatSummaryType": "OdinUnranked"}, {"wins": 0, "aggregatedStats": {}, "losses": 0, "modifyDate": 1436975451000, "playerStatSummaryType": "RankedSolo5x5"}, {"wins": 401, "aggregatedStats": {"totalChampionKills": 5479, "totalTurretsKilled": 584, "totalMinionKills": 72280, "totalNeutralMinionsKilled": 9473, "totalAssists": 6508}, "modifyDate": 1454346606000, "playerStatSummaryType": "Unranked"}, {"wins": 55, "aggregatedStats": {"totalChampionKills": 650, "totalTurretsKilled": 41, "totalMinionKills": 4071, "totalNeutralMinionsKilled": 592, "totalAssists": 714}, "modifyDate": 1453340769000, "playerStatSummaryType": "Unranked3x3"}], "summonerId": 50034}