{"playerStatSummaries": [{"wins": 52, "aggregatedStats": {"totalChampionKills": 904, "totalTurretsKilled": 47, "totalAssists": 1752}, "modifyDate": 1460764414000, "playerStatSummaryType": "AramUnranked5x5"}, {"wins": 125, "aggregatedStats": {"totalChampionKills": 1743, "totalTurretsKilled": 270, "totalMinionKills": 35344, "totalNeutralMinionsKilled": 2024, "totalAssists": 1949}, "modifyDate": 1453330635000, "playerStatSummaryType": "CAP5x5"}, {"wins": 60, "aggregatedStats": {"totalTurretsKilled": 111, "averageNodeNeutralize": 8, "maxTeamObjective": 2, "totalAssists": 398, "maxNodeNeutralize": 8, "averageChampionsKilled": 11, "averageNodeNeutralizeAssist": 0, "averageTeamObjective": 2, "averageAssists": 7, "maxChampionsKilled": 11, "totalNodeCapture": 11, "maxNodeNeutralizeAssist": 0, "totalNeutralMinionsKilled": 627, "averageTotalPlayerScore": 1518, "maxTotalPlayerScore": 1518, "maxNodeCaptureAssist": 2, "totalChampionKills": 443, "averageNodeCaptureAssist": 2, "maxObjectivePlayerScore": 1137, "totalNodeNeutralize": 8, "totalMinionKills": 4807, "averageObjectivePlayerScore": 1137, "maxNodeCapture": 11, "maxCombatPlayerScore": 381, "averageNodeCapture": 11, "maxAssists": 7, "averageCombatPlayerScore": 381, "averageNumDeaths": 2}, "modifyDate": 1453330635000, "playerStatSummaryType": "CoopVsAI"}, {"wins": 9, "aggregatedStats": {"averageAssists": 4, "averageNodeNeutralize": 3, "averageChampionsKilled": 6, "totalAssists": 99, "maxNodeNeutralize": 9, "maxTeamObjective": 2, "averageNodeNeutralizeAssist": 2, "averageTeamObjective": 1, "maxNodeCapture": 12, "maxChampionsKilled": 15, "totalNodeCapture": 126, "maxNodeNeutralizeAssist": 4, "averageTotalPlayerScore": 783, "maxTotalPlayerScore": 1619, "maxNodeCaptureAssist": 3, "totalChampionKills": 117, "averageNodeCaptureAssist": 2, "totalNodeNeutralize": 83, "maxObjectivePlayerScore": 1144, "averageObjectivePlayerScore": 546, "maxCombatPlayerScore": 715, "averageNodeCapture": 5, "maxAssists": 9, "averageCombatPlayerScore": 237, "averageNumDeaths": 7}, "modifyDate": 1453330635000, "playerStatSummaryType": "OdinUnranked"}, {"wins": 2, "aggregatedStats": {"totalChampionKills": 23, "totalTurretsKilled": 0, "totalMinionKills": 494, "totalNeutralMinionsKilled": 23, "totalAssists": 45}, "losses": 1, "modifyDate": 1460560616000, "playerStatSummaryType": "RankedSolo5x5"}, {"wins": 0, "aggregatedStats": {}, "losses": 0, "modifyDate": 1404864413000, "playerStatSummaryType": "RankedTeam5x5"}, {"wins": 2, "aggregatedStats": {"totalChampionKills": 24, "totalTurretsKilled": 4, "totalMinionKills": 293, "totalNeutralMinionsKilled": 36, "totalAssists": 32}, "modifyDate": 1461369798000, "playerStatSummaryType": "URF"}, {"wins": 781, "aggregatedStats": {"totalChampionKills": 9840, "totalTurretsKilled": 1622, "totalMinionKills": 179175, "totalNeutralMinionsKilled": 17978, "totalAssists": 12518}, "modifyDate": 1461782936000, "playerStatSummaryType": "Unranked"}, {"wins": 1, "aggregatedStats": {"totalChampionKills": 30, "totalTurretsKilled": 3, "totalMinionKills": 389, "totalNeutralMinionsKilled": 79, "totalAssists": 33}, "modifyDate": 1461782936000, "playerStatSummaryType": "Unranked3x3"}], "summonerId": 53873}