{"playerStatSummaries": [{"wins": 31, "aggregatedStats": {"totalChampionKills": 551, "totalTurretsKilled": 60, "totalMinionKills": 7591, "totalNeutralMinionsKilled": 1036, "totalAssists": 335}, "modifyDate": 1453327460000, "playerStatSummaryType": "CAP5x5"}, {"wins": 226, "aggregatedStats": {"totalChampionKills": 2546, "totalTurretsKilled": 374, "totalMinionKills": 19689, "totalNeutralMinionsKilled": 2352, "totalAssists": 1434}, "modifyDate": 1453327460000, "playerStatSummaryType": "CoopVsAI"}, {"wins": 2, "aggregatedStats": {"averageAssists": 4, "averageNodeNeutralize": 3, "averageChampionsKilled": 8, "totalAssists": 23, "maxNodeNeutralize": 6, "maxTeamObjective": 2, "averageNodeNeutralizeAssist": 1, "averageTeamObjective": 0, "maxNodeCapture": 9, "maxChampionsKilled": 21, "totalNodeCapture": 22, "maxNodeNeutralizeAssist": 1, "averageTotalPlayerScore": 874, "maxTotalPlayerScore": 1858, "maxNodeCaptureAssist": 2, "totalChampionKills": 40, "averageNodeCaptureAssist": 2, "totalNodeNeutralize": 16, "maxObjectivePlayerScore": 917, "averageObjectivePlayerScore": 508, "maxCombatPlayerScore": 941, "averageNodeCapture": 5, "maxAssists": 8, "averageCombatPlayerScore": 366, "averageNumDeaths": 7}, "modifyDate": 1453327460000, "playerStatSummaryType": "OdinUnranked"}, {"wins": 0, "aggregatedStats": {}, "losses": 0, "modifyDate": 1357928529000, "playerStatSummaryType": "RankedTeam5x5"}, {"wins": 2, "aggregatedStats": {}, "modifyDate": 1460848559000, "playerStatSummaryType": "KingPoro"}, {"wins": 1, "aggregatedStats": {}, "modifyDate": 1461078194000, "playerStatSummaryType": "Ascension"}, {"wins": 19, "aggregatedStats": {"totalChampionKills": 380, "totalTurretsKilled": 47, "totalMinionKills": 3152, "totalNeutralMinionsKilled": 91, "totalAssists": 260}, "modifyDate": 1461530300000, "playerStatSummaryType": "URF"}, {"wins": 170, "aggregatedStats": {"totalChampionKills": 3366, "totalTurretsKilled": 160, "totalAssists": 5421}, "modifyDate": 1461591334000, "playerStatSummaryType": "AramUnranked5x5"}, {"wins": 1474, "aggregatedStats": {"totalChampionKills": 23892, "totalTurretsKilled": 3083, "totalMinionKills": 356737, "totalNeutralMinionsKilled": 38907, "totalAssists": 21188}, "modifyDate": 1461770051000, "playerStatSummaryType": "Unranked"}, {"wins": 11, "aggregatedStats": {"totalChampionKills": 182, "totalTurretsKilled": 19, "totalMinionKills": 2454, "totalNeutralMinionsKilled": 192, "totalAssists": 144}, "modifyDate": 1461770051000, "playerStatSummaryType": "Unranked3x3"}, {"wins": 102, "aggregatedStats": {"totalChampionKills": 1289, "totalTurretsKilled": 205, "totalMinionKills": 24717, "totalNeutralMinionsKilled": 1146, "totalAssists": 2050}, "losses": 104, "modifyDate": 1461780437000, "playerStatSummaryType": "RankedSolo5x5"}], "summonerId": 74494}